cdmn_mcp_server/__init__.py
cdmn_mcp_server/llm_client_mock.py
cdmn_mcp_server/server_fully_generic.py
cdmn_mcp_server/business_rules/__init__.py
cdmn_mcp_server/business_rules/insurance.py
cdmn_mcp_server/business_rules/loan.py
cdmn_mcp_server/prompts/__init__.py
cdmn_mcp_server/prompts/llm_usage_guide.md
cdmn_mcp_server/prompts/natural_language_parser.py
cdmn_mcp_server/rules/dish.dmn.xml
cdmn_mcp_server/rules/insurance_premium.dmn.xml
cdmn_mcp_server/rules/loan_approval.dmn.xml
cdmn_mcp_server-3.2.1.dist-info/licenses/LICENSE
cdmn_mcp_server-3.2.1.dist-info/METADATA
cdmn_mcp_server-3.2.1.dist-info/WHEEL
cdmn_mcp_server-3.2.1.dist-info/entry_points.txt
cdmn_mcp_server-3.2.1.dist-info/top_level.txt
cdmn_mcp_server-3.2.1.dist-info/RECORD
