Metadata-Version: 2.4
Name: cdmn-mcp-server
Version: 3.2.1
Summary: 하이브리드 DMN MCP 서버 - DRD 지원, cDMN API와 표준 XML 파싱을 모두 지원하는 FastMCP 기반 의사결정 서버
Home-page: https://github.com/rickjang/cdmn-mcp-server
Author: rickjang
Author-email: rickjang <rickjang@example.com>
License: MIT
Project-URL: Homepage, https://github.com/rickjang/cdmn-mcp-server
Project-URL: Documentation, https://github.com/rickjang/cdmn-mcp-server#readme
Project-URL: Repository, https://github.com/rickjang/cdmn-mcp-server
Project-URL: Bug Tracker, https://github.com/rickjang/cdmn-mcp-server/issues
Keywords: mcp,dmn,decision,rules,engine,fastmcp,llm,natural language,cdmn
Classifier: Development Status :: 4 - Beta
Classifier: Intended Audience :: Developers
Classifier: License :: OSI Approved :: MIT License
Classifier: Operating System :: OS Independent
Classifier: Programming Language :: Python :: 3
Classifier: Programming Language :: Python :: 3.11
Classifier: Programming Language :: Python :: 3.12
Classifier: Topic :: Software Development :: Libraries :: Python Modules
Classifier: Topic :: Scientific/Engineering :: Artificial Intelligence
Classifier: Topic :: Office/Business :: Financial
Requires-Python: >=3.11
License-File: LICENSE
Requires-Dist: fastmcp>=0.1.0
Requires-Dist: pydantic>=2.0.0
Requires-Dist: aiofiles>=23.0.0
Requires-Dist: cdmn>=2.0.0
Requires-Dist: idp-engine>=0.12.0
Provides-Extra: dev
Requires-Dist: pytest>=7.0.0; extra == "dev"
Requires-Dist: pytest-asyncio>=0.21.0; extra == "dev"
Requires-Dist: httpx>=0.24.0; extra == "dev"
Dynamic: author
Dynamic: home-page
Dynamic: license-file
Dynamic: requires-python
